timestamp2vec/Timestamp2Vec.py
timestamp2vec/__init__.py
timestamp2vec/helper_functions.py
timestamp2vec/encoder_VAE/keras_metadata.pb
timestamp2vec/encoder_VAE/saved_model.pb
timestamp2vec/encoder_VAE/variables/variables.data-00000-of-00001
timestamp2vec/encoder_VAE/variables/variables.index
timestamp2vec/important_variables/latent_dim.txt
timestamp2vec/important_variables/max_val.npy
timestamp2vec/important_variables/min_val.npy
timestamp2vec-1.0.0.dist-info/LICENSE
timestamp2vec-1.0.0.dist-info/METADATA
timestamp2vec-1.0.0.dist-info/WHEEL
timestamp2vec-1.0.0.dist-info/top_level.txt
timestamp2vec-1.0.0.dist-info/RECORD
